energyid_webhooks/__init__.py
energyid_webhooks/_version.py
energyid_webhooks/client.py
energyid_webhooks/client_v2.py
energyid_webhooks/metercatalog.py
energyid_webhooks/payload.py
energyid_webhooks/py.typed
energyid_webhooks/webhookpolicy.py
energyid_webhooks-0.0.14.dist-info/licenses/LICENSE
energyid_webhooks-0.0.14.dist-info/METADATA
energyid_webhooks-0.0.14.dist-info/WHEEL
energyid_webhooks-0.0.14.dist-info/top_level.txt
energyid_webhooks-0.0.14.dist-info/RECORD
