Metadata-Version: 2.4
Name: energyid-webhooks
Version: 0.0.14
Summary: Light weight Python package to interface with EnergyID Webhooks
Author-email: Jan Pecinovsky <jan@energieid.be>, Oscar Swyns <oscar@energieid.be>
License-Expression: MIT
Project-URL: Homepage, https://github.com/EnergieID/energyid-webhooks-py
Project-URL: Bug Tracker, https://github.com/EnergieID/energyid-webhooks-py/issues
Classifier: Development Status :: 3 - Alpha
Classifier: Intended Audience :: Developers
Classifier: Intended Audience :: Science/Research
Classifier: Natural Language :: English
Classifier: Operating System :: OS Independent
Classifier: Programming Language :: Python :: 3
Classifier: Topic :: Scientific/Engineering
Classifier: Topic :: Scientific/Engineering :: Mathematics
Classifier: Topic :: Scientific/Engineering :: Physics
Classifier: Topic :: Software Development :: Libraries :: Python Modules
Classifier: Typing :: Typed
Requires-Python: >=3.11
License-File: LICENSE
Requires-Dist: aiohttp>=3.11.12
Requires-Dist: backoff>=2.2.1
Requires-Dist: requests>=2.32.3
Dynamic: license-file
